bucket/__init__.py
bucket/__main__.py
bucket/cli.py
bucket/core.py
bkt-6.0.0.dist-info/LICENSE
bkt-6.0.0.dist-info/METADATA
bkt-6.0.0.dist-info/WHEEL
bkt-6.0.0.dist-info/entry_points.txt
bkt-6.0.0.dist-info/top_level.txt
bkt-6.0.0.dist-info/RECORD
