Metadata-Version: 2.1
Name: bkt
Version: 6.0.0
Summary: Dependency manager for any language, for free, no subscriptions.
Author: astridot
Author-email: pixilreal@gmail.com
Classifier: Programming Language :: Python :: 3
Classifier: License :: OSI Approved :: GNU General Public License v3 (GPLv3)
Classifier: Operating System :: OS Independent
Requires-Python: >=3.12
License-File: LICENSE
Requires-Dist: typer
